catwalk/__init__.py
catwalk/cli.py
catwalk/utils.py
catppuccin_catwalk-0.4.0.dist-info/entry_points.txt
catppuccin_catwalk-0.4.0.dist-info/WHEEL
catppuccin_catwalk-0.4.0.dist-info/METADATA
catppuccin_catwalk-0.4.0.dist-info/RECORD
