Metadata-Version: 2.1
Name: catppuccin-catwalk
Version: 0.4.0
Summary: Part of catppuccin/toolbox, to generate preview a single composite screenshot for the four flavours
Home-page: https://github.com/catppuccin/toolbox
License: MIT
Author: Catppuccin Org
Author-email: core@catppuccin.com
Requires-Python: >=3.8,<4.0
Classifier: License :: OSI Approved :: MIT License
Classifier: Programming Language :: Python :: 3
Classifier: Programming Language :: Python :: 3.10
Classifier: Programming Language :: Python :: 3.8
Classifier: Programming Language :: Python :: 3.9
Requires-Dist: Pillow (>=9.2.0,<10.0.0)
Project-URL: Repository, https://github.com/catppuccin/toolbox
